temod_flask/__init__.py
temod_flask/blueprint/__init__.py
temod_flask/blueprint/configurable_blueprint.py
temod_flask/blueprint/exceptions.py
temod_flask/blueprint/utils/__init__.py
temod_flask/blueprint/utils/exceptions.py
temod_flask/blueprint/utils/paginator.py
temod_flask/ext/__init__.py
temod_flask/ext/forms.py
temod_flask/rest/__init__.py
temod_flask/rest/endpoint.py
temod_flask/rest/exceptions.py
temod_flask/security/authentification/__init__.py
temod_flask/security/authentification/authenticators.py
temod_flask/security/authentification/exceptions.py
temod_flask/security/authentification/users.py
temod_flask/security/authority/__init__.py
temod_flask/security/authority/alarm.py
temod_flask/security/authority/exceptions.py
temod_flask/security/authority/gardian.py
temod_flask/security/authority/right.py
temod_flask/security/authority/utils.py
temod_flask/utils/__init__.py
temod_flask/utils/content_readers.py
temod_flask/utils/content_writers.py
temod_flask/utils/external_api.py
temod_flask-2.2.5.dist-info/licenses/LICENSE.txt
temod_flask-2.2.5.dist-info/METADATA
temod_flask-2.2.5.dist-info/WHEEL
temod_flask-2.2.5.dist-info/top_level.txt
temod_flask-2.2.5.dist-info/RECORD
