Metadata-Version: 2.4
Name: temod-flask
Version: 2.2.5
Summary: Connects python-flask features with Temod data models
Author-email: PyAxolotl <abdellatifzied.saada@gmail.com>
Project-URL: Homepage, https://github.com/TuburboMajus/temod-flask
Project-URL: Bug Tracker, https://github.com/TuburboMajus/temod-flask/issues
Classifier: Programming Language :: Python :: 3
Classifier: License :: OSI Approved :: MIT License
Classifier: Operating System :: OS Independent
Requires-Python: >=3.7
License-File: LICENSE.txt
Requires-Dist: oauthlib>=3.2.2
Requires-Dist: python-json-logger>=2.0.4
Requires-Dist: requests>=2.28.2
Requires-Dist: temod-forms>=2.0.0
Requires-Dist: temod-open-api>=1.0.0
Dynamic: license-file
